pumpit/__main__.py
pumpit-0.4.dist-info/LICENSE
pumpit-0.4.dist-info/METADATA
pumpit-0.4.dist-info/WHEEL
pumpit-0.4.dist-info/entry_points.txt
pumpit-0.4.dist-info/top_level.txt
pumpit-0.4.dist-info/RECORD
