Metadata-Version: 2.1
Name: pumpit
Version: 0.4
Summary: UNKNOWN
Home-page: UNKNOWN
Author: Thomas Oberbichler
Author-email: thomas.oberbichler@gmail.com
License: UNKNOWN
Platform: UNKNOWN
Requires-Dist: click
